ZdModelTools/__init__.py
ZdModelTools/DataEvaluate/Data_Evaluate.py
ZdModelTools/DataEvaluate/Evaluate_Tools.py
ZdModelTools/DataEvaluate/__init__.py
ZdModelTools/DataEvaluate/load_inner_score_log_result.py
ZdModelTools/DataPrepare/__init__.py
ZdModelTools/DataPrepare/load_data.py
ZdModelTools-0.1.9.dist-info/METADATA
ZdModelTools-0.1.9.dist-info/WHEEL
ZdModelTools-0.1.9.dist-info/top_level.txt
ZdModelTools-0.1.9.dist-info/RECORD
